[
    {
        "user_name": "ImissToddStarnes",
        "time": "17 June, 2021",
        "context": "China - overtaking the USA one step at a time..",
        "good": "16",
        "bad": "11",
        "replies": [
            {
                "user_name": "RedTeepee",
                "time": "17 June, 2021",
                "context": "ISS in space 22 years.  First trip to CSS, today.",
                "good": "20",
                "bad": "0",
                "replies": []
            },
            {
                "user_name": "ewin79510",
                "time": "17 June, 2021",
                "context": "on Biden's watch...Biden = FAILURE",
                "good": "7",
                "bad": "2",
                "replies": []
            },
            {
                "user_name": "jon61586",
                "time": "17 June, 2021",
                "context": "How is it overtaking if we have done this 23 years ago? Seems to me more like catching up.",
                "good": "3",
                "bad": "0",
                "replies": []
            }
        ]
    },
    {
        "user_name": "fba981",
        "time": "17 June, 2021",
        "context": "It'd make me nervous getting in a rocket that's mounted to a large stick, placed in a giant bottle and has a fuse on the bottom of it. It also mentions something on the side about \"with report\".",
        "good": "20",
        "bad": "4",
        "replies": []
    },
    {
        "user_name": "SteventheDodger#1fan",
        "time": "17 June, 2021",
        "context": "Nice to see their salute to the true leaders in space exploration by wearing the good old red, white and blue!",
        "good": "31",
        "bad": "3",
        "replies": []
    },
    {
        "user_name": "ImissToddStarnes",
        "time": "17 June, 2021",
        "context": "I for one, welcome my new Chinese overlords..",
        "good": "2",
        "bad": "4",
        "replies": []
    },
    {
        "error": "error"
    },
    {
        "user_name": "descrest",
        "time": "17 June, 2021",
        "context": "They must have velcro on the bottom of their shoes????",
        "good": "11",
        "bad": "0",
        "replies": [
            {
                "user_name": "ck1969",
                "time": "17 June, 2021",
                "context": "No, It's just that new artificial gravity device that they installed next to the virus incubators...",
                "good": "14",
                "bad": "0",
                "replies": []
            }
        ]
    },
    {
        "user_name": "ewin79510",
        "time": "17 June, 2021",
        "context": "A Chinese space station...it'll be broken within a month",
        "good": "5",
        "bad": "1",
        "replies": []
    },
    {
        "user_name": "Femadurkadur",
        "time": "17 June, 2021",
        "context": "We should intentionally send space debris in their trajectory ",
        "good": "0",
        "bad": "1",
        "replies": []
    },
    {
        "user_name": "yo666",
        "time": "17 June, 2021",
        "context": "Somebody better shoot that thing down.",
        "good": "14",
        "bad": "9",
        "replies": [
            {
                "user_name": "opaque5488",
                "time": "17 June, 2021",
                "context": "That's so Wong on so many levels.",
                "good": "7",
                "bad": "1",
                "replies": [
                    {
                        "user_name": "bowfishslayer614",
                        "time": "17 June, 2021",
                        "context": "HaHa, you spelt wrong wong, how did you get it wong",
                        "good": "0",
                        "bad": "0",
                        "replies": []
                    }
                ]
            },
            {
                "user_name": "bowfishslayer614",
                "time": "17 June, 2021",
                "context": "It is made in China, it will come down on its own, two days after its 90 day warranty",
                "good": "13",
                "bad": "0",
                "replies": [
                    {
                        "user_name": "spiderweb2",
                        "time": "17 June, 2021",
                        "context": "Ahahahahahahah",
                        "good": "0",
                        "bad": "0",
                        "replies": []
                    },
                    {
                        "user_name": "Femadurkadur",
                        "time": "17 June, 2021",
                        "context": "Warranty?",
                        "good": "0",
                        "bad": "0",
                        "replies": []
                    },
                    {
                        "user_name": "BlueCorn",
                        "time": "17 June, 2021",
                        "context": "Well the Indians better start calling them now to get that warranty extended",
                        "good": "0",
                        "bad": "0",
                        "replies": []
                    }
                ]
            }
        ]
    },
    {
        "user_name": "rexkarrs",
        "time": "17 June, 2021",
        "context": "the may get to MARS the meeting with PUTIN was stupid waste of time Russia is 2nd rate  at best instead of dealing with China they are dealing with a minor despot that runs a country full of alcoholics",
        "good": "2",
        "bad": "3",
        "replies": []
    },
    {
        "user_name": "skibum2",
        "time": "17 June, 2021",
        "context": "So how much is Biden being paid for this? You Know his fingers are in it.",
        "good": "2",
        "bad": "2",
        "replies": []
    },
    {
        "user_name": "czr561",
        "time": "17 June, 2021",
        "context": "Oh no, Covid in SPACE!!!😂😂",
        "good": "3",
        "bad": "2",
        "replies": []
    },
    {
        "user_name": "Death-to-the-Monarchy",
        "time": "17 June, 2021",
        "context": "Watch your cokes!",
        "good": "1",
        "bad": "0",
        "replies": []
    },
    {
        "user_name": "waveslin",
        "time": "17 June, 2021",
        "context": "And mysteriously, American satellites will start to disappear.",
        "good": "12",
        "bad": "0",
        "replies": []
    },
    {
        "user_name": "imfortrump2020",
        "time": "17 June, 2021",
        "context": "good luck on your re-entry (sarc)",
        "good": "0",
        "bad": "0",
        "replies": []
    },
    {
        "user_name": "dirkdiggler2",
        "time": "17 June, 2021",
        "context": "I hope they have a good ventilation system for when they serve kimchi for dinner. \n\"me so stinky\"",
        "good": "2",
        "bad": "1",
        "replies": []
    },
    {
        "user_name": "NonyoBiz",
        "time": "17 June, 2021",
        "context": "all I can say is...knowing the Chinese fuse boxes I have, I wouldn't bet my life on it.....",
        "good": "0",
        "bad": "0",
        "replies": []
    },
    {
        "user_name": "tarfu_bohica",
        "time": "17 June, 2021",
        "context": "And it only took 50 years longer than the West.",
        "good": "6",
        "bad": "2",
        "replies": []
    },
    {
        "user_name": "dwtwin",
        "time": "17 June, 2021",
        "context": "What's the betting line on when this thing becomes another multi-ton flaming projectile endangering earth?",
        "good": "4",
        "bad": "3",
        "replies": []
    },
    {
        "user_name": "Don'tTouchThat",
        "time": "17 June, 2021",
        "context": "This will be another uncontrolled plunge back to earth!",
        "good": "0",
        "bad": "0",
        "replies": [
            {
                "user_name": "cleanundies",
                "time": "17 June, 2021",
                "context": "\"prunge\".",
                "good": "1",
                "bad": "0",
                "replies": [
                    {
                        "user_name": "Don'tTouchThat",
                        "time": "18 June, 2021",
                        "context": "Prunge, that's what the chinese astronauts will do in their pants when it plunges to earth.",
                        "good": "0",
                        "bad": "0",
                        "replies": []
                    }
                ]
            }
        ]
    },
    {
        "user_name": "Christian97",
        "time": "17 June, 2021",
        "context": "Congrats Chinamen, welcome to the 1960's!  lolz",
        "good": "1",
        "bad": "2",
        "replies": [
            {
                "user_name": "jimmy3",
                "time": "17 June, 2021",
                "context": "?!?!  We had a space station in the 60s?",
                "good": "0",
                "bad": "0",
                "replies": [
                    {
                        "user_name": "Christian97",
                        "time": "17 June, 2021",
                        "context": "No, we just went to the moon instead, lol. Mir and Skylab may have been in the 70's",
                        "good": "0",
                        "bad": "0",
                        "replies": [
                            {
                                "user_name": "jimmy3",
                                "time": "17 June, 2021",
                                "context": "That's what I thought.  China is doing the smart thing and getting a space station as a stepping stone to space colonization.\n\nLets hope America can beat them to the first inhabited colony in space.",
                                "good": "0",
                                "bad": "0",
                                "replies": []
                            }
                        ]
                    }
                ]
            }
        ]
    },
    {
        "user_name": "cajunconservative427",
        "time": "17 June, 2021",
        "context": "So they going to have Chinese take out in space? Maybe they can deliver to the space station?",
        "good": "1",
        "bad": "1",
        "replies": []
    },
    {
        "user_name": "cleanundies",
        "time": "17 June, 2021",
        "context": "\"Chinese Moon Locket\". Made of plastic and won't last very long. But cheap, and you can get them at Walmart.",
        "good": "1",
        "bad": "1",
        "replies": []
    },
    {
        "user_name": "roadglideon1018",
        "time": "17 June, 2021",
        "context": "Yet they are still a developing nation , and pollution laws don’t mater ",
        "good": "50",
        "bad": "4",
        "replies": []
    },
    {
        "user_name": "rjvet",
        "time": "17 June, 2021",
        "context": "Wonder if the \"Big Guy\" got his cut? Guess they be waiting for their congratulatory call from Comrade \"Big Guy\".",
        "good": "38",
        "bad": "3",
        "replies": []
    },
    {
        "user_name": "jimmy3",
        "time": "17 June, 2021",
        "context": "Very cool.  Its sad that America has ceded our advantages in space exploration to the Chinese.  Whomever is first in space colonization will have their culture dominate the next few centuries.",
        "good": "4",
        "bad": "8",
        "replies": [
            {
                "user_name": "NewarkPI",
                "time": "17 June, 2021",
                "context": "um, we actually DO have people in space too",
                "good": "3",
                "bad": "1",
                "replies": []
            }
        ]
    },
    {
        "user_name": "wayne5600303",
        "time": "17 June, 2021",
        "context": "Dog crates were unloaded labeled as lunch.",
        "good": "4",
        "bad": "1",
        "replies": []
    },
    {
        "user_name": "Death-to-the-Monarchy",
        "time": "17 June, 2021",
        "context": "Hopefully they didn't bring any viruses.",
        "good": "2",
        "bad": "1",
        "replies": []
    },
    {
        "user_name": "NCLEO1992",
        "time": "17 June, 2021",
        "context": "They seem to be standing.",
        "good": "4",
        "bad": "0",
        "replies": []
    },
    {
        "user_name": "okie2021",
        "time": "17 June, 2021",
        "context": "Megnetized shoes, Velcro, or a studio set? I don't think artificial gravity has been perfected yet, they are firmly on the floor instead of floating.",
        "good": "60",
        "bad": "6",
        "replies": [
            {
                "user_name": "jimmy3",
                "time": "17 June, 2021",
                "context": "In our space station we have 'standing clips' on the floor you can put your feet in to stay stable.",
                "good": "18",
                "bad": "1",
                "replies": []
            },
            {
                "user_name": "MrMagooPacksHeat",
                "time": "17 June, 2021",
                "context": "No, you don't understand. This picture was taken 1 minute before launch and they're trying to prove they're better than their American counterparts by standing up during launch. Notice the bathroom handles on the right - in case they need to steady themselves.",
                "good": "10",
                "bad": "8",
                "replies": []
            },
            {
                "user_name": "wmvan498",
                "time": "19 June, 2021",
                "context": "I’d guess the photo was taken in a mock-up on earth.",
                "good": "0",
                "bad": "0",
                "replies": []
            }
        ]
    },
    {
        "user_name": "metalhead2000",
        "time": "17 June, 2021",
        "context": "I wonder if they took Covid-19 virus into space with them...........",
        "good": "6",
        "bad": "1",
        "replies": []
    },
    {
        "user_name": "Marines19235",
        "time": "17 June, 2021",
        "context": "We are falling behind in all areas of concerning China",
        "good": "0",
        "bad": "4",
        "replies": []
    },
    {
        "user_name": "DontReadReplies",
        "time": "17 June, 2021",
        "context": "Why are they standing? they're supposed to be floating in space.",
        "good": "13",
        "bad": "2",
        "replies": [
            {
                "user_name": "deepthought",
                "time": "17 June, 2021",
                "context": "They aren't in space...",
                "good": "11",
                "bad": "5",
                "replies": []
            },
            {
                "user_name": "jimmy3",
                "time": "17 June, 2021",
                "context": "Yeah, how would /SCIENTISTS/ figure out how to stick to the 'floor' of the space station?\n\nThey certainly wouldn't install clips on the floor you can put your feet in to stop floating when working..............",
                "good": "5",
                "bad": "5",
                "replies": []
            }
        ]
    },
    {
        "user_name": "blasto",
        "time": "17 June, 2021",
        "context": "The US did this, what, 40 years ago? How did the Chinese do it now? They stole our technology…..again.",
        "good": "5",
        "bad": "3",
        "replies": [
            {
                "user_name": "jerryclc",
                "time": "17 June, 2021",
                "context": "Clinton sold them our rocket technology.",
                "good": "7",
                "bad": "0",
                "replies": [
                    {
                        "user_name": "NewarkPI",
                        "time": "17 June, 2021",
                        "context": "along with our Nuke technology",
                        "good": "4",
                        "bad": "0",
                        "replies": []
                    }
                ]
            }
        ]
    },
    {
        "user_name": "Death-to-the-Monarchy",
        "time": "17 June, 2021",
        "context": "I wish everyone a \"happy ending\".",
        "good": "9",
        "bad": "0",
        "replies": []
    },
    {
        "user_name": "whatbillofrights",
        "time": "17 June, 2021",
        "context": "Watch out folks they could bring another China virus with them.",
        "good": "3",
        "bad": "1",
        "replies": []
    },
    {
        "user_name": "withoutremorse768",
        "time": "17 June, 2021",
        "context": "C.hinese\nO.rbital\nV.iral\nI.nstitute of\nD.eath",
        "good": "9",
        "bad": "3",
        "replies": []
    },
    {
        "user_name": "proudtexan189",
        "time": "17 June, 2021",
        "context": "oh look they have Biden for president buttons on their suits ",
        "good": "10",
        "bad": "0",
        "replies": [
            {
                "user_name": "jamiec",
                "time": "17 June, 2021",
                "context": "No Malarkey in Chinese",
                "good": "2",
                "bad": "0",
                "replies": []
            }
        ]
    },
    {
        "error": "error"
    },
    {
        "user_name": "searchkgbchurch",
        "time": "17 June, 2021",
        "context": "Well that's good.  Too bad their space program is just another part of their military.  This is the same thing as saying that space force has it's own space station in Space.",
        "good": "2",
        "bad": "0",
        "replies": []
    },
    {
        "user_name": "twistedmister",
        "time": "17 June, 2021",
        "context": "90% of the tech they are using is from stolen patents and research.  \nThere's a reason why their Mars rover looks suspiciously like the U.S. Curiosity Rover. \nTheir Space Station will also be suspiciously similar to the I.S.S.",
        "good": "78",
        "bad": "17",
        "replies": [
            {
                "error": "error"
            },
            {
                "error": "error"
            },
            {
                "user_name": "Lowerland",
                "time": "17 June, 2021",
                "context": "How did you work out that figure 90%?",
                "good": "12",
                "bad": "7",
                "replies": []
            },
            {
                "user_name": "v12tommy",
                "time": "18 June, 2021",
                "context": "Did you see the video animation of their mars rover landing? They literally copied a 10 year old video NASA made, almost frame by frame, just substituting in their own spacecraft.",
                "good": "1",
                "bad": "0",
                "replies": []
            },
            {
                "user_name": "dog🐺man",
                "time": "19 June, 2021",
                "context": "The plans for the Mars probes are not secret. Anyone can download them.",
                "good": "0",
                "bad": "0",
                "replies": []
            }
        ]
    },
    {
        "error": "error"
    },
    {
        "error": "error"
    },
    {
        "user_name": "jamiec",
        "time": "17 June, 2021",
        "context": "Virologists no doubt.",
        "good": "11",
        "bad": "1",
        "replies": []
    },
    {
        "user_name": "fangflyer2",
        "time": "17 June, 2021",
        "context": "And China stole all of that knowledge from America and Russia....",
        "good": "14",
        "bad": "2",
        "replies": [
            {
                "user_name": "Lowerland",
                "time": "17 June, 2021",
                "context": "How did you know? ",
                "good": "3",
                "bad": "2",
                "replies": [
                    {
                        "user_name": "constitutiongal",
                        "time": "17 June, 2021",
                        "context": "that's how they were able to...with help from ignorants such as you. ",
                        "good": "1",
                        "bad": "2",
                        "replies": []
                    }
                ]
            }
        ]
    },
    {
        "user_name": "KnightsTemplar",
        "time": "17 June, 2021",
        "context": "All paid for by the American public and their love for cheap one time use throw away communist chinese made garbage. ",
        "good": "9",
        "bad": "1",
        "replies": [
            {
                "user_name": "gsaogb",
                "time": "17 June, 2021",
                "context": "capitalism.",
                "good": "4",
                "bad": "0",
                "replies": []
            },
            {
                "user_name": "selfrespect",
                "time": "17 June, 2021",
                "context": "Don't blame the Chinese for the cheap products. Blame the American politicians and American businessmen who make more money abroad while closing manufacturing in America!",
                "good": "4",
                "bad": "0",
                "replies": []
            }
        ]
    },
    {
        "user_name": "thehappydem",
        "time": "17 June, 2021",
        "context": "Let me guess. This is Biden’s fault.",
        "good": "0",
        "bad": "1",
        "replies": [
            {
                "user_name": "dgcatty",
                "time": "17 June, 2021",
                "context": "Nah, Biden doesn't even remember what he had for breakfast.",
                "good": "2",
                "bad": "0",
                "replies": []
            }
        ]
    },
    {
        "user_name": "not-politically-correct",
        "time": "17 June, 2021",
        "context": "I sure hope it's built with better quality than the stuff we buy at Walmart",
        "good": "17",
        "bad": "1",
        "replies": []
    },
    {
        "user_name": "oldsoldier141",
        "time": "17 June, 2021",
        "context": "New Wuhan Viral space lab ",
        "good": "3",
        "bad": "1",
        "replies": []
    },
    {
        "user_name": "MYGOD,MYCOUNTRY,MYFREEDOM",
        "time": "17 June, 2021",
        "context": "WHAT CHINAS NOT TELLING YOU: THESE AINT ASTRONAUTS. THEY ARE HONEST WUHAN LAB PROFESSORS. ",
        "good": "3",
        "bad": "0",
        "replies": []
    },
    {
        "user_name": "NewarkPI",
        "time": "17 June, 2021",
        "context": "Hunter Biden was paid $500 TRILLION as a consultant on this project, with 10% to 'The Big Guy'....",
        "good": "8",
        "bad": "1",
        "replies": []
    },
    {
        "user_name": "cnytocfl",
        "time": "17 June, 2021",
        "context": "Astronauts or spies?",
        "good": "2",
        "bad": "0",
        "replies": []
    },
    {
        "user_name": "7roundtripstothemoon",
        "time": "17 June, 2021",
        "context": "Another launch just like Covid ",
        "good": "4",
        "bad": "0",
        "replies": []
    },
    {
        "user_name": "4cx35000c",
        "time": "17 June, 2021",
        "context": "I'm curious how much of that technology was stolen from other countries.",
        "good": "34",
        "bad": "6",
        "replies": [
            {
                "user_name": "selfrespect",
                "time": "17 June, 2021",
                "context": "LOTS!",
                "good": "6",
                "bad": "1",
                "replies": []
            },
            {
                "user_name": "OrangeTag",
                "time": "17 June, 2021",
                "context": "ALL of it.",
                "good": "34",
                "bad": "1",
                "replies": []
            },
            {
                "user_name": "Lowerland",
                "time": "17 June, 2021",
                "context": "Thinking of too good of oneself will only be left behind by others! ",
                "good": "5",
                "bad": "7",
                "replies": [
                    {
                        "user_name": "4cx35000c",
                        "time": "17 June, 2021",
                        "context": "Thanks for that tidbit of wisdom, Confucius.",
                        "good": "4",
                        "bad": "0",
                        "replies": []
                    }
                ]
            },
            {
                "user_name": "dc9qc",
                "time": "17 June, 2021",
                "context": "There is absolutely no reason to steal from us when it's cheaper just to buy it which is what they do usually.",
                "good": "0",
                "bad": "0",
                "replies": [
                    {
                        "user_name": "4cx35000c",
                        "time": "18 June, 2021",
                        "context": "That's fine IF the technology is for sale, which isn't always the case.",
                        "good": "0",
                        "bad": "0",
                        "replies": []
                    }
                ]
            },
            {
                "user_name": "alexalex123427",
                "time": "17 June, 2021",
                "context": "I bet China would become the first country to retrieve samples from Mars, which no other countries could did, because western world stuck in its own stupid and idiot political conspiracy.",
                "good": "27",
                "bad": "2",
                "replies": []
            }
        ]
    },
    {
        "user_name": "kcview",
        "time": "17 June, 2021",
        "context": "Love how their feet are tied down for the obligatory martial salute.",
        "good": "2",
        "bad": "0",
        "replies": []
    },
    {
        "user_name": "tcfan",
        "time": "17 June, 2021",
        "context": "I wonder how long the oxygen levels will take to drop. ",
        "good": "5",
        "bad": "0",
        "replies": []
    },
    {
        "user_name": "deepthinkingbrian",
        "time": "17 June, 2021",
        "context": "Notice how the three are the same race. If this was the USA the three would be different races and genders.",
        "good": "18",
        "bad": "1",
        "replies": []
    },
    {
        "user_name": "MartelTheHammer",
        "time": "17 June, 2021",
        "context": "To experiment with gain of function in a weightless environment.",
        "good": "21",
        "bad": "2",
        "replies": [
            {
                "user_name": "logginheimer",
                "time": "17 June, 2021",
                "context": "It doesn't look weightless to me.",
                "good": "8",
                "bad": "0",
                "replies": []
            },
            {
                "user_name": "rogerusa018",
                "time": "17 June, 2021",
                "context": "The next Chinese virus is coming to a hood near you.",
                "good": "9",
                "bad": "3",
                "replies": []
            }
        ]
    },
    {
        "user_name": "thehappydem",
        "time": "17 June, 2021",
        "context": "They stole the technology from us and built it with funds from the WH all since Biden took over.",
        "good": "1",
        "bad": "3",
        "replies": []
    },
    {
        "user_name": "BlackCloud277",
        "time": "17 June, 2021",
        "context": "Watch for the guided missiles to start launching as a demonstration of military supremacy. ",
        "good": "1",
        "bad": "0",
        "replies": []
    },
    {
        "user_name": "From_the_desk_of_🍊🤡",
        "time": "17 June, 2021",
        "context": "While China explores in space, Abbott in the US builds 3 foot walls with crowd funding.",
        "good": "3",
        "bad": "6",
        "replies": [
            {
                "user_name": "gnacman",
                "time": "17 June, 2021",
                "context": "I guess you love terrorists and gangs and illegal weapons?",
                "good": "1",
                "bad": "1",
                "replies": []
            }
        ]
    },
    {
        "user_name": "broadwayltd235",
        "time": "17 June, 2021",
        "context": "Well if that space station has the same manufacturing quality control like everything else we’ve bought from China those guys won’t last long",
        "good": "34",
        "bad": "6",
        "replies": []
    },
    {
        "user_name": "spike97809",
        "time": "17 June, 2021",
        "context": "They had to design special filters to keep rice out of the various systems onboard.",
        "good": "11",
        "bad": "4",
        "replies": []
    },
    {
        "user_name": "Harambé's-₲ay-Stepcousin🦍",
        "time": "17 June, 2021",
        "context": "Just more of American and Russian intellectual technology stolen by China because they are too dumb to come up with the technology of their own. Facts are NOT racist!",
        "good": "4",
        "bad": "2",
        "replies": [
            {
                "user_name": "good_things_never_last",
                "time": "17 June, 2021",
                "context": "Green screens?",
                "good": "1",
                "bad": "0",
                "replies": []
            }
        ]
    },
    {
        "error": "error"
    },
    {
        "user_name": "eckman",
        "time": "17 June, 2021",
        "context": "With the poor quality of Chinese made things, it takes a lot of guts and commitment to the communist party to fly one of those......",
        "good": "5",
        "bad": "0",
        "replies": []
    },
    {
        "user_name": "From_the_desk_of_🍊🤡",
        "time": "17 June, 2021",
        "context": "Trump's Space Force saw the rocket launch but failed to keep track of it.  Trump said it's just a Johnson.",
        "good": "1",
        "bad": "4",
        "replies": [
            {
                "user_name": "tyredcynic",
                "time": "17 June, 2021",
                "context": "Is that your excuse for how you got that banana stuck up your keister?",
                "good": "2",
                "bad": "0",
                "replies": []
            }
        ]
    },
    {
        "user_name": "gnacman",
        "time": "17 June, 2021",
        "context": "If it works as well as most of their products, it'll come crashing down in about 6 months",
        "good": "3",
        "bad": "0",
        "replies": []
    },
    {
        "user_name": "tyredcynic",
        "time": "17 June, 2021",
        "context": "China has zero welfare and zero \"social programs\"; they can afford all kinds of cool toys.",
        "good": "3",
        "bad": "0",
        "replies": []
    },
    {
        "user_name": "RWCM",
        "time": "17 June, 2021",
        "context": "Hope the Commies take their buddy Hunter on their next flight to space and leave him there!!!  Maybe they could take the “Big Guy” too???",
        "good": "3",
        "bad": "0",
        "replies": []
    },
    {
        "user_name": "anythingthatworks",
        "time": "17 June, 2021",
        "context": "And the Paris accord calls China \"a developing country\".",
        "good": "44",
        "bad": "3",
        "replies": []
    },
    {
        "user_name": "rockwod",
        "time": "17 June, 2021",
        "context": "I bought a used chinese built tractor, if they built their space station anything like they build tractors run for cover because that sucker is coming down.",
        "good": "4",
        "bad": "0",
        "replies": []
    },
    {
        "error": "error"
    },
    {
        "user_name": "GreenScissors",
        "time": "17 June, 2021",
        "context": "This garbage shouldn't even be in American news.",
        "good": "4",
        "bad": "4",
        "replies": []
    },
    {
        "user_name": "awebapprentice",
        "time": "17 June, 2021",
        "context": "The travel time is down from the two days it took to reach China’s earlier experimental space stations, a result of a \"great many breakthroughs and innovations,\"\n\nBreaking through firewalls and innovating new ways to steal technology.",
        "good": "85",
        "bad": "34",
        "replies": [
            {
                "error": "error"
            },
            {
                "user_name": "__JOHN__",
                "time": "17 June, 2021",
                "context": "They probably stole every usable part.",
                "good": "10",
                "bad": "10",
                "replies": []
            },
            {
                "user_name": "the.altruistic.psarchotic",
                "time": "17 June, 2021",
                "context": "Hint to media socialites and most journos :  when a Chinese virus is unleashed from there, it probably can’t  be spun as accidental bat droppings.",
                "good": "6",
                "bad": "4",
                "replies": []
            }
        ]
    },
    {
        "user_name": "RWCM",
        "time": "17 June, 2021",
        "context": "Did Fauci fund this Chinese project also??? ",
        "good": "4",
        "bad": "1",
        "replies": []
    },
    {
        "error": "error"
    },
    {
        "user_name": "*cynic*",
        "time": "17 June, 2021",
        "context": "So what's going to fall to earth upon reentry this time?",
        "good": "10",
        "bad": "1",
        "replies": [
            {
                "user_name": "BlueBandAid",
                "time": "17 June, 2021",
                "context": "Test tubes from Wuhan.....",
                "good": "9",
                "bad": "0",
                "replies": []
            }
        ]
    },
    {
        "user_name": "brownwatervet",
        "time": "17 June, 2021",
        "context": "Yeah I'm convinced. Nice try China.",
        "good": "11",
        "bad": "1",
        "replies": []
    },
    {
        "user_name": "dgcatty",
        "time": "17 June, 2021",
        "context": "Maybe they can launch a virus out into space and F up the whole galaxy next time.",
        "good": "0",
        "bad": "0",
        "replies": []
    },
    {
        "user_name": "FakeNewsDumDums",
        "time": "17 June, 2021",
        "context": "How exactly did we let this happen?? How do we know it's not going to be a Battle Station or a Hub for spying? ",
        "good": "3",
        "bad": "2",
        "replies": [
            {
                "user_name": "CorbinDallas",
                "time": "17 June, 2021",
                "context": "Its both...",
                "good": "1",
                "bad": "1",
                "replies": []
            }
        ]
    },
    {
        "user_name": "good_things_never_last",
        "time": "17 June, 2021",
        "context": "Cool green screen!",
        "good": "6",
        "bad": "0",
        "replies": []
    },
    {
        "user_name": "geocho",
        "time": "17 June, 2021",
        "context": "Obviously they're not concerned or freaking out about 'aliens' following their air/spacecraft.",
        "good": "0",
        "bad": "0",
        "replies": []
    },
    {
        "user_name": "lctommyboy",
        "time": "17 June, 2021",
        "context": "Still trying to control the population I see. -3",
        "good": "2",
        "bad": "0",
        "replies": []
    },
    {
        "error": "error"
    },
    {
        "user_name": "martell77",
        "time": "17 June, 2021",
        "context": "They testing if covid can live in space?",
        "good": "1",
        "bad": "0",
        "replies": []
    },
    {
        "user_name": "gunsnguitars",
        "time": "17 June, 2021",
        "context": "Splicing viruses in space.",
        "good": "5",
        "bad": "1",
        "replies": [
            {
                "user_name": "jose9056",
                "time": "17 June, 2021",
                "context": "Might be possible.  Containment would certainly be easier.  Lab leak?  On, so sorry.  You are lost in space.",
                "good": "2",
                "bad": "0",
                "replies": []
            }
        ]
    },
    {
        "user_name": "joec1961",
        "time": "17 June, 2021",
        "context": "“Made in China”…..SNAP ",
        "good": "0",
        "bad": "0",
        "replies": []
    },
    {
        "user_name": "coltor",
        "time": "17 June, 2021",
        "context": "Weird, I don't see any signs of no gravity in the photo.",
        "good": "4",
        "bad": "1",
        "replies": []
    },
    {
        "user_name": "Perplexed9942",
        "time": "17 June, 2021",
        "context": "Congrats!  Built on stolen American Tech.",
        "good": "7",
        "bad": "0",
        "replies": []
    },
    {
        "user_name": "californiamojo",
        "time": "17 June, 2021",
        "context": "Good for them.",
        "good": "0",
        "bad": "3",
        "replies": []
    },
    {
        "user_name": "pblooney46",
        "time": "17 June, 2021",
        "context": "Everyone take cover to avoid the 1st stage booster rocket that falls who knows where!",
        "good": "1",
        "bad": "0",
        "replies": []
    },
    {
        "user_name": "averagedeplorable",
        "time": "17 June, 2021",
        "context": "China should send thank you notes to all the firms and governments they stole from to get to this point",
        "good": "5",
        "bad": "0",
        "replies": []
    },
    {
        "user_name": "theomnipotentstate",
        "time": "17 June, 2021",
        "context": "Great news for the glorious and magnificent CCP. \nNow they can work on undermining the United States in space. \nProgress is beautiful. \nProgress is good.",
        "good": "0",
        "bad": "0",
        "replies": []
    },
    {
        "user_name": "coolyd223",
        "time": "17 June, 2021",
        "context": "I thought we already put Tang into space.",
        "good": "10",
        "bad": "1",
        "replies": [
            {
                "user_name": "Perplexed9942",
                "time": "17 June, 2021",
                "context": "OK that's good!",
                "good": "1",
                "bad": "1",
                "replies": []
            }
        ]
    },
    {
        "user_name": "cajunconservative427",
        "time": "17 June, 2021",
        "context": "Wonder how much their toilet cost? Maybe they just \"hang\" it out a port hole! Probably just bag it and trow it out as space waste.",
        "good": "0",
        "bad": "1",
        "replies": [
            {
                "user_name": "From_the_desk_of_🍊🤡",
                "time": "17 June, 2021",
                "context": "word is Bezos is going up to collect the waste baggies",
                "good": "2",
                "bad": "0",
                "replies": []
            }
        ]
    },
    {
        "user_name": "From_the_desk_of_🍊🤡",
        "time": "17 June, 2021",
        "context": "Trump thought he had China beat with his dumb Space Force. LOL",
        "good": "2",
        "bad": "4",
        "replies": [
            {
                "user_name": "martell77",
                "time": "17 June, 2021",
                "context": "This is WHY he created the Space Force, gruber. What did the dems do? I know, the dems took bribes...",
                "good": "4",
                "bad": "0",
                "replies": []
            },
            {
                "user_name": "constitutiongal",
                "time": "17 June, 2021",
                "context": "so dumb the democrats kept it. Lord save us from the asinine likes of you. ",
                "good": "2",
                "bad": "0",
                "replies": []
            }
        ]
    },
    {
        "user_name": "lukebusy66",
        "time": "17 June, 2021",
        "context": "Let's see what happens when they try to come back.",
        "good": "1",
        "bad": "0",
        "replies": [
            {
                "user_name": "Launchallvipers",
                "time": "17 June, 2021",
                "context": "Why? China has been sending astronauts  (taikonauts) to space for nearly 20 years..",
                "good": "1",
                "bad": "0",
                "replies": [
                    {
                        "user_name": "lukebusy66",
                        "time": "17 June, 2021",
                        "context": "They had no idea where their latest satellite would come down.",
                        "good": "0",
                        "bad": "0",
                        "replies": []
                    }
                ]
            }
        ]
    },
    {
        "user_name": "davidwjones58",
        "time": "17 June, 2021",
        "context": "I suspect it you looked at the equipment, it would all say \"stolen in USA\"",
        "good": "1",
        "bad": "2",
        "replies": [
            {
                "user_name": "joecrowe77",
                "time": "17 June, 2021",
                "context": "Have you opened up your computer and checked where its parts came from?",
                "good": "0",
                "bad": "0",
                "replies": []
            }
        ]
    },
    {
        "user_name": "buffalo",
        "time": "17 June, 2021",
        "context": "\"Chinese crew enters new space station module for 3-month mission\".  Made possible by American money, Chinese students educated at U.S. colleges, theft of and forced technology.",
        "good": "3",
        "bad": "5",
        "replies": []
    },
    {
        "error": "error"
    },
    {
        "user_name": "aesops.retreat",
        "time": "17 June, 2021",
        "context": "They look like they are just STANDING there?  No Floating?",
        "good": "1",
        "bad": "0",
        "replies": [
            {
                "user_name": "joecrowe77",
                "time": "17 June, 2021",
                "context": "That is how it works on a real space station not one on MGM's back lot.",
                "good": "0",
                "bad": "1",
                "replies": []
            }
        ]
    },
    {
        "user_name": "WerWeist513",
        "time": "17 June, 2021",
        "context": "The ISS has already received flyers for Chinese take-out.",
        "good": "3",
        "bad": "0",
        "replies": []
    },
    {
        "user_name": "cormac02325",
        "time": "17 June, 2021",
        "context": "Look they can't make a frying pan that lasts a year, there will be freeze dried and vacuum sealed chinaman floating around up in no time.",
        "good": "2",
        "bad": "0",
        "replies": []
    },
    {
        "user_name": "hillary’s_cankles_speak",
        "time": "17 June, 2021",
        "context": "Tune in tomorrow, when the Commienauts will demonstrate wok cooking in space.  It should be a real hot time.",
        "good": "9",
        "bad": "2",
        "replies": [
            {
                "user_name": "rogerusa018",
                "time": "17 June, 2021",
                "context": "Rats in sesame oil.  Yum.",
                "good": "2",
                "bad": "2",
                "replies": []
            }
        ]
    },
    {
        "user_name": "retiredandtired22590",
        "time": "17 June, 2021",
        "context": "Trump had them beat and in less than a year under Biden they surpassed us. Unbelievable.",
        "good": "7",
        "bad": "1",
        "replies": [
            {
                "user_name": "From_the_desk_of_🍊🤡",
                "time": "17 June, 2021",
                "context": "Where was Trump's Space Force?",
                "good": "1",
                "bad": "4",
                "replies": [
                    {
                        "user_name": "rogerusa018",
                        "time": "17 June, 2021",
                        "context": "Didn't you hear?  President Senile Sippy Cup has dismantled it, with great assistance from the FBI.",
                        "good": "1",
                        "bad": "2",
                        "replies": []
                    }
                ]
            },
            {
                "user_name": "joecrowe77",
                "time": "17 June, 2021",
                "context": "Trump had no one beat except himself.",
                "good": "3",
                "bad": "4",
                "replies": []
            }
        ]
    },
    {
        "user_name": "bl_from_fla035",
        "time": "17 June, 2021",
        "context": "How does one say \"Hold Your Breath as Wrong as Possiber\" in Chinese ??",
        "good": "0",
        "bad": "0",
        "replies": []
    },
    {
        "user_name": "mop2022",
        "time": "17 June, 2021",
        "context": "meanwhile black slaves declare country wide riots, and we solving bathroom assignment problem, including in the Army",
        "good": "3",
        "bad": "1",
        "replies": []
    },
    {
        "user_name": "kyyankeefan",
        "time": "17 June, 2021",
        "context": "MSNBC just announced their names:  Moe, Rarry, and Curry.",
        "good": "4",
        "bad": "1",
        "replies": []
    },
    {
        "user_name": "jose9056",
        "time": "17 June, 2021",
        "context": "Nice uniforms, but so 1980's.  Why not copy Musk's designs?",
        "good": "5",
        "bad": "1",
        "replies": [
            {
                "user_name": "Perplexed9942",
                "time": "17 June, 2021",
                "context": "They copied everything else",
                "good": "2",
                "bad": "0",
                "replies": []
            }
        ]
    },
    {
        "user_name": "Zebulon1776",
        "time": "17 June, 2021",
        "context": "And then they salute the world goodbye forever ....",
        "good": "0",
        "bad": "0",
        "replies": []
    },
    {
        "user_name": "sandiglas",
        "time": "17 June, 2021",
        "context": "It's amazing how the Chinese are moving forward with their space program in leaps and bounds.  One wouldn't think it possible when their deputy chief designer says things like \"So the astronauts can have a good rest in space which should make them less tired.\"",
        "good": "1",
        "bad": "0",
        "replies": []
    },
    {
        "user_name": "divisifiedfarm",
        "time": "17 June, 2021",
        "context": "Just like America, all they can do is go 'round and around and around and around and around and......",
        "good": "0",
        "bad": "1",
        "replies": []
    },
    {
        "user_name": "GreenGoggles",
        "time": "17 June, 2021",
        "context": "Where they will send the Wuhan evidence into orbit",
        "good": "2",
        "bad": "0",
        "replies": []
    },
    {
        "user_name": "my1970america832",
        "time": "17 June, 2021",
        "context": "Watch your heads that thing will be falling soon.",
        "good": "1",
        "bad": "0",
        "replies": []
    },
    {
        "user_name": "xjustcuriousx",
        "time": "17 June, 2021",
        "context": "They seem to have gravity in that picture?",
        "good": "1",
        "bad": "0",
        "replies": []
    },
    {
        "user_name": "perrytheplatypus988",
        "time": "17 June, 2021",
        "context": "That space station will serve as excellent target practice for our new Space Force.",
        "good": "1",
        "bad": "1",
        "replies": []
    },
    {
        "user_name": "timmyd",
        "time": "17 June, 2021",
        "context": "...yeah, they stole most of their tech from the US.\nHunter was the go-between and he also got \"10 for the Big Guy.\"",
        "good": "4",
        "bad": "0",
        "replies": []
    },
    {
        "user_name": "sissyliberalsmakemesick",
        "time": "17 June, 2021",
        "context": "PROBABLY GOING TO SPREAD THE CHINA VIRUS ON THE MOON....",
        "good": "2",
        "bad": "0",
        "replies": []
    },
    {
        "user_name": "jsr0008",
        "time": "17 June, 2021",
        "context": "Made possible by stolen U.S. technologies, and Democr☭ts.\nUniversities, labs, research facilities, etc....",
        "good": "7",
        "bad": "1",
        "replies": []
    },
    {
        "user_name": "marleydude",
        "time": "17 June, 2021",
        "context": "In other news, previous residence of the international space station mistake the picture of the Chinese crew, thinking it highly resembled the interior of the international space station!",
        "good": "0",
        "bad": "0",
        "replies": []
    },
    {
        "user_name": "RoRo400",
        "time": "17 June, 2021",
        "context": "Go China!\nThe world needs competition... especially our forever slacking country",
        "good": "2",
        "bad": "2",
        "replies": [
            {
                "user_name": "63-Polara",
                "time": "17 June, 2021",
                "context": "Whatever, Ping Ling.",
                "good": "0",
                "bad": "0",
                "replies": []
            }
        ]
    },
    {
        "user_name": "AZbil",
        "time": "17 June, 2021",
        "context": "Beijing reports their space scientist are busily on various theoretical procedures to bring them or at least some of them back to earth. \nWhen that's resolved the next goal will to bring the mighty adventurers back alive.",
        "good": "0",
        "bad": "1",
        "replies": []
    },
    {
        "user_name": "Sleepyjoe312",
        "time": "17 June, 2021",
        "context": "They also successfully killed over 600k Americans. Accident or not they should be held accountable but we don’t have a real man in the oval. Did you see Putin laugh in that old fool’s face. He was laughing at all of us ",
        "good": "1",
        "bad": "0",
        "replies": [
            {
                "user_name": "avoiceinthewoods",
                "time": "17 June, 2021",
                "context": "And apparently we may have actually paid some of the research costs for them to do it.\n\nI also assert China did not independently launch its space craft/station, there is a whole lot of stolen US and Russian Technology put to use to make those launches possible.",
                "good": "1",
                "bad": "0",
                "replies": []
            }
        ]
    },
    {
        "user_name": "How_bout_this?!",
        "time": "17 June, 2021",
        "context": "All accomplished on copying American technology! Thanks Joe!!",
        "good": "10",
        "bad": "3",
        "replies": []
    },
    {
        "user_name": "sharkmeisterm",
        "time": "17 June, 2021",
        "context": "That's fine except they were aiming for the moon.\nFilm at eleven",
        "good": "1",
        "bad": "0",
        "replies": []
    },
    {
        "user_name": "caphastings605",
        "time": "17 June, 2021",
        "context": "With Space Force one day the U.S.A. will have manned orbiting military bases.",
        "good": "4",
        "bad": "0",
        "replies": []
    },
    {
        "user_name": "fakeitgoodnasa",
        "time": "17 June, 2021",
        "context": "I spotted several three dollar bills floating around in the Chinese 'space station'..",
        "good": "0",
        "bad": "0",
        "replies": []
    },
    {
        "user_name": "happywingnut",
        "time": "17 June, 2021",
        "context": "Amazing what can be achieved with stolen technology.",
        "good": "16",
        "bad": "2",
        "replies": []
    },
    {
        "user_name": "hereintexas",
        "time": "17 June, 2021",
        "context": "Unless they are wearing Velcro or magnetic shoes, not sure how they are able to stand so easily on the floor without floating around? Can't imagine the Chinese would stage such an event? (just kidding, everyone knows they wouldn't hesitate.  FYI- regarding COVID Lab Leak \"Occam's razor, also spelled Ockham's razor, also called law of economy or law of parsimony, principle stated by the Scholastic philosopher William of Ockham (1285–1347/49) that pluralitas non est ponenda sine necessitate, “plurality should not be posited without necessity.” The principle gives precedence to simplicity:, makes allot of sense to me, the virus leaked from the LAB unless proven otherwise from not China + WHO, they lost their credibility a very long time ago! As the leftist would say- FOLLOW THE SCIENCE!",
        "good": "3",
        "bad": "0",
        "replies": [
            {
                "user_name": "kilowattt245",
                "time": "17 June, 2021",
                "context": "“Unless they are wearing Velcro or magnetic shoes, not sure how they are able to stand so easily on the floor without floating around?”\n \nInteresting observation.",
                "good": "0",
                "bad": "0",
                "replies": []
            }
        ]
    },
    {
        "user_name": "alexxx888",
        "time": "17 June, 2021",
        "context": "It's easy for China to go to space...all they have to do is get 2 billion of them to climb on each other's shoulders.",
        "good": "1",
        "bad": "1",
        "replies": []
    },
    {
        "user_name": "skihunter",
        "time": "17 June, 2021",
        "context": "Stolen tech from the US and others.",
        "good": "5",
        "bad": "1",
        "replies": []
    },
    {
        "user_name": "whoareyousowiseinthewaysofscience",
        "time": "17 June, 2021",
        "context": "only way to escape communism in China.",
        "good": "3",
        "bad": "0",
        "replies": []
    },
    {
        "user_name": "supernaut869",
        "time": "17 June, 2021",
        "context": "I wonder if the food is still warm when it gets there.",
        "good": "0",
        "bad": "0",
        "replies": []
    },
    {
        "user_name": "roadapples",
        "time": "17 June, 2021",
        "context": "They must be planning to infect the Moon and Mars, just in case we plan to build bases there...",
        "good": "1",
        "bad": "0",
        "replies": []
    },
    {
        "user_name": "goldspecie208",
        "time": "17 June, 2021",
        "context": "They did it the American way.  They were so diligent in copying everything they included the made in America label.",
        "good": "2",
        "bad": "0",
        "replies": []
    },
    {
        "user_name": "sturner451",
        "time": "17 June, 2021",
        "context": "I wonder what freeze dried General Tso's tastes like.",
        "good": "3",
        "bad": "0",
        "replies": [
            {
                "user_name": "krassniamonk",
                "time": "17 June, 2021",
                "context": "Probably pretty good, especially when another country paid the bill!",
                "good": "1",
                "bad": "0",
                "replies": []
            }
        ]
    },
    {
        "user_name": "narivaboy12",
        "time": "17 June, 2021",
        "context": ". Pictures showed them Nie Haisheng, 56,  Liu Boming, 54, and Tang Hongbo, 45 locally known as covid-19, covid- 20, and covid-21. When they return they will be quarantined or not.  WHO will know?",
        "good": "2",
        "bad": "2",
        "replies": []
    },
    {
        "user_name": "Scratchingpost",
        "time": "17 June, 2021",
        "context": "Ground control to Major Haisheng\nYou've really made the grade\nAnd the papers want to know whose shirts you wear\nNow it's time to leave the capsule if you dare",
        "good": "1",
        "bad": "0",
        "replies": []
    },
    {
        "user_name": "krassniamonk",
        "time": "17 June, 2021",
        "context": "Does it matter who/where the tech came from if it improves their ability to extend their influence to orbit? Meanwhile, the lib US government is fanning the flames on phantom inclusion/diversity issues. Setting the stage for de-dollarization and the eventual US shift to mediocrity.",
        "good": "3",
        "bad": "0",
        "replies": []
    },
    {
        "user_name": "oldgolffart",
        "time": "17 June, 2021",
        "context": "Space stations everywhere...the need traffic lights on Mars....it's a new day",
        "good": "0",
        "bad": "0",
        "replies": []
    },
    {
        "user_name": "OlivePaw",
        "time": "17 June, 2021",
        "context": "Oh yeah, Chinese delivery in space.",
        "good": "1",
        "bad": "0",
        "replies": [
            {
                "user_name": "billspill",
                "time": "17 June, 2021",
                "context": "Perhaps deadly packages pointed back at Earth.",
                "good": "0",
                "bad": "0",
                "replies": []
            }
        ]
    },
    {
        "user_name": "Chinapirate1",
        "time": "17 June, 2021",
        "context": "Haha. Probably a fake background. Hope they took some Wuhan Flu bats with them.",
        "good": "2",
        "bad": "0",
        "replies": []
    },
    {
        "user_name": "kilowattt245",
        "time": "17 June, 2021",
        "context": "I wonder what the orbiting path of the Chinese space station so I can keep a watch for falling debris.",
        "good": "4",
        "bad": "0",
        "replies": []
    },
    {
        "user_name": "Heavymetal61520",
        "time": "17 June, 2021",
        "context": "Beijing, \"WE HAVE BIG FUCCA PROBLEM\"..!",
        "good": "0",
        "bad": "0",
        "replies": []
    },
    {
        "user_name": "BlueUmbrella",
        "time": "17 June, 2021",
        "context": "Hate to say this but:  They are way ahead of us now!  We have to depend on others to get to the international space station, SAD!",
        "good": "3",
        "bad": "5",
        "replies": []
    },
    {
        "user_name": "kilowattt245",
        "time": "17 June, 2021",
        "context": "I wonder how much it is costing the Chinese government in funds to have their own space station in orbit instead of hooking up with the ISS?",
        "good": "0",
        "bad": "0",
        "replies": [
            {
                "user_name": "p1037x",
                "time": "17 June, 2021",
                "context": "It does not matter, the US borrows money from China and pays interest. So, they have a lot of money while we are broke.",
                "good": "0",
                "bad": "0",
                "replies": []
            }
        ]
    },
    {
        "user_name": "jsr0008",
        "time": "17 June, 2021",
        "context": "How's the African Space Program coming along?",
        "good": "2",
        "bad": "1",
        "replies": []
    },
    {
        "user_name": "caphastings605",
        "time": "17 June, 2021",
        "context": "The first orbiting Space Force base will be named Trump base 1.",
        "good": "4",
        "bad": "0",
        "replies": []
    },
    {
        "user_name": "hotrodfordanda$2bill",
        "time": "17 June, 2021",
        "context": "a result of a \"great many breakthroughs and innovations\"\n\nSo who did they steal it from, the US or Russia?",
        "good": "4",
        "bad": "0",
        "replies": [
            {
                "user_name": "homies",
                "time": "17 June, 2021",
                "context": "Both.",
                "good": "1",
                "bad": "0",
                "replies": []
            }
        ]
    },
    {
        "user_name": "z28rules",
        "time": "17 June, 2021",
        "context": "They will be making a new movie while they are at the space station called Spies In Space",
        "good": "3",
        "bad": "0",
        "replies": []
    },
    {
        "user_name": "kilowattt245",
        "time": "17 June, 2021",
        "context": "I hope their space station stays together and doesn’t malfunction like some of the merchandise they sell to the U.S. that is inferior.",
        "good": "4",
        "bad": "0",
        "replies": []
    },
    {
        "user_name": "ok_whatever210",
        "time": "17 June, 2021",
        "context": "Was Biden at the ceremony  cutting the ribbon for uncle xi?",
        "good": "1",
        "bad": "0",
        "replies": []
    },
    {
        "user_name": "f.foo",
        "time": "17 June, 2021",
        "context": "Something tells me they won't be using Gender Dysphoria Pronouns to address each other or Hanging a BLM  or Rainbow Flag from thier Space Station. That's part of the reason China is Eating America's lunch. Bidens Weak Feeble WokeHouse is a puts a big grin on China's Communist leaders.",
        "good": "2",
        "bad": "0",
        "replies": [
            {
                "user_name": "ImissToddStarnes",
                "time": "17 June, 2021",
                "context": "Bidens Weak Feeble WokeHouse is a puts a big grin on China's Communist leaders.\n\nYou should try that sentence again..",
                "good": "0",
                "bad": "2",
                "replies": [
                    {
                        "user_name": "f.foo",
                        "time": "17 June, 2021",
                        "context": "Indeed. With Siri as my copilot... it happens from time to time, but I think most can rise above the grammar to understand the meaning. ",
                        "good": "1",
                        "bad": "0",
                        "replies": []
                    }
                ]
            }
        ]
    },
    {
        "error": "error"
    },
    {
        "user_name": "firstnlast",
        "time": "17 June, 2021",
        "context": "made possible only by cheating, lying and stealing from others..",
        "good": "6",
        "bad": "2",
        "replies": []
    },
    {
        "user_name": "impeachbidenanddahoe",
        "time": "17 June, 2021",
        "context": "China Astronaut: Hewwo, dis is chinese space station. Sun very bright. I tink sum ting wong.",
        "good": "1",
        "bad": "2",
        "replies": []
    },
    {
        "user_name": "Bigdubya",
        "time": "17 June, 2021",
        "context": "I know one thing, their is no way I would want to be in space in anything made in China. ",
        "good": "1",
        "bad": "0",
        "replies": []
    },
    {
        "user_name": "p1037x",
        "time": "17 June, 2021",
        "context": "Courtesy of stolen US technology. Thanks to our universities and Chinese hacking into out corporations.",
        "good": "3",
        "bad": "1",
        "replies": []
    },
    {
        "user_name": "shouthard",
        "time": "17 June, 2021",
        "context": "The only truly innovative and creative thing that the Chinese Communist Party is doing is not launching a rocket, a stealth fighter an aircraft carrier or any other landmark based on stolen technology.  \n\nThey are leading the world in persecution of minorities.  More than any other nation, they are finding new ways to oppress Christians, Uyghurs, Catholics or anyone else who simply doesn't think the thoughts they want them to think.  Arrest, torture, reeducation, imprisonment--they are truly innovative and champions at this sick craft.  The other stuff is just ... meh...immitation.",
        "good": "0",
        "bad": "1",
        "replies": []
    },
    {
        "user_name": "kilowattt245",
        "time": "17 June, 2021",
        "context": "“’This represents the first time Chinese have entered their own space station,’ state broadcaster CCTV said on its nightly news broadcast.”\n \nI would think CCTV would stand for close-circuit TV; however in China, it might stand for Chinese-Communist TV.",
        "good": "2",
        "bad": "0",
        "replies": []
    },
    {
        "user_name": "Pudrucker",
        "time": "17 June, 2021",
        "context": "Did they take a vial of COVID for the road? ",
        "good": "1",
        "bad": "0",
        "replies": []
    },
    {
        "user_name": "outhier",
        "time": "17 June, 2021",
        "context": "So when is China sending somebody to the moon or Mars?",
        "good": "1",
        "bad": "0",
        "replies": [
            {
                "error": "error"
            }
        ]
    },
    {
        "user_name": "johnmcclane004",
        "time": "17 June, 2021",
        "context": "Have a friend who taught English in China, she said when a company moved their manufacturing to China, Chinese workers would work their for 6 months then open a factory across the street making the same thing. Our Politicians have aloud this to happen. We keep voting these crooks in they don’t care who lines their pockets China Russia.",
        "good": "1",
        "bad": "0",
        "replies": [
            {
                "user_name": "kilowattt245",
                "time": "17 June, 2021",
                "context": "\"...aloud...\"\n\nallowed",
                "good": "0",
                "bad": "0",
                "replies": []
            },
            {
                "user_name": "mander457",
                "time": "17 June, 2021",
                "context": "their=there. Aloud=allowed. Punctuation is also a wonderful tool to help others understand what you are TRYING to say.",
                "good": "0",
                "bad": "1",
                "replies": []
            }
        ]
    },
    {
        "user_name": "mander457",
        "time": "17 June, 2021",
        "context": "How wonderful! Now they can develop and launch new virus' back to specific nations on earth whenever they choose. No pesky \"rules\" or inspectors to monitor or provide curbs on what they do. World domination is their goal.",
        "good": "1",
        "bad": "0",
        "replies": []
    },
    {
        "user_name": "koofasa",
        "time": "17 June, 2021",
        "context": "I wonder how many died before they did it successfully?  There will be no news about that.",
        "good": "2",
        "bad": "0",
        "replies": []
    },
    {
        "user_name": "ryszardp",
        "time": "17 June, 2021",
        "context": "space virus?",
        "good": "1",
        "bad": "0",
        "replies": []
    },
    {
        "user_name": "seanptc",
        "time": "17 June, 2021",
        "context": "They get their own space station?  Why do we have to share ours?",
        "good": "1",
        "bad": "0",
        "replies": [
            {
                "user_name": "nick1958295",
                "time": "17 June, 2021",
                "context": "Because we borrow.",
                "good": "0",
                "bad": "0",
                "replies": []
            }
        ]
    },
    {
        "user_name": "chasb1",
        "time": "17 June, 2021",
        "context": "The first thing the crew did was call for takeout ...",
        "good": "0",
        "bad": "0",
        "replies": []
    },
    {
        "user_name": "homies",
        "time": "17 June, 2021",
        "context": "Hey, where's our communication satellite? Do you think the Chinese took it?",
        "good": "1",
        "bad": "0",
        "replies": []
    },
    {
        "user_name": "bidenslyin",
        "time": "17 June, 2021",
        "context": "In further news the U.S. had more killings in Atlanta, and Chicago. Due to Transgender Jimmy is now called Jane. BLM has completed the list of things they want to steal and CNN boasts Biden had his first controlled bowel movement without diapers. ",
        "good": "4",
        "bad": "0",
        "replies": [
            {
                "user_name": "mander457",
                "time": "17 June, 2021",
                "context": "Yeah, the \"woke snowflakes\" are really concerned about the important stuff. NOT!",
                "good": "1",
                "bad": "0",
                "replies": []
            }
        ]
    },
    {
        "user_name": "maddog49",
        "time": "17 June, 2021",
        "context": "GENTLEMEN -- We won't be able to hurl enough insults to UNDO the fact that China has a space station that is somewhat like the International Space Station.  What is funny is how Russia is still partnered with us even though its government is newly divested of the U.S. dollar.  Will Russia switch over to partnering with China in space?\n\nIf so, Space X has a lot of work to do.\n\nStolen or otherwise, China is showing it has caught up with the U.S. in advanced technology.  \n\nThe threat of President Xi incrementally implementing Orwell 1984 Totalitarianism still looms.  Xi doesn't do enough Totalitarianism to collapse his own economy.  But he sure can use the technology to hit enemies with Totalitarianism.  The hapless Uighurs are the guinea pigs.",
        "good": "8",
        "bad": "2",
        "replies": [
            {
                "user_name": "kilowattt245",
                "time": "17 June, 2021",
                "context": "\"Will Russia switch over to partnering with China in space?\"\n\nThat's probably already happening.",
                "good": "2",
                "bad": "0",
                "replies": []
            },
            {
                "user_name": "kilowattt245",
                "time": "17 June, 2021",
                "context": "“Space X has a lot of work to do.”\n \nThat’s right…hurry up! So we can start building Space-Hotels orbiting around Earth and them also providing the civilian transportation to these Space-Hotels.",
                "good": "0",
                "bad": "0",
                "replies": []
            }
        ]
    },
    {
        "user_name": "BuckFoeJiden",
        "time": "17 June, 2021",
        "context": "Yeah, but is the rocket thruster section going to uncontrollably crash back to Earth?",
        "good": "1",
        "bad": "0",
        "replies": []
    },
    {
        "user_name": "marzejka302",
        "time": "17 June, 2021",
        "context": "Standing on the floor of the space station in zero gravity.......hmmmmm.....interesting!",
        "good": "9",
        "bad": "2",
        "replies": [
            {
                "user_name": "jhousdan",
                "time": "17 June, 2021",
                "context": "our station has velcro straps that allow the astronauts/cosmonauts to stand in place on one surface or another. not sure what you're insinuating, but there's no reason to think that the Chinese wouldn't copy that just like they copy everything else.",
                "good": "2",
                "bad": "1",
                "replies": []
            }
        ]
    },
    {
        "user_name": "cj134",
        "time": "17 June, 2021",
        "context": "Meanwhile Europe has nothing, no bragging rights at all, pathetic.",
        "good": "2",
        "bad": "0",
        "replies": []
    },
    {
        "user_name": "durnisch",
        "time": "17 June, 2021",
        "context": "We gotta get better at competing with these guys, and stop technology theft.",
        "good": "2",
        "bad": "0",
        "replies": [
            {
                "user_name": "nick1958295",
                "time": "17 June, 2021",
                "context": "We are past the point of return. Our education was done a mortal blow while theirs gets better and better.",
                "good": "0",
                "bad": "0",
                "replies": []
            }
        ]
    },
    {
        "user_name": "theconchrepublic",
        "time": "17 June, 2021",
        "context": "Does this mean faster delivery?.....no msg..",
        "good": "0",
        "bad": "0",
        "replies": []
    },
    {
        "user_name": "2cynical4words",
        "time": "17 June, 2021",
        "context": "That is quite an accomplishment.  Also quite scary.",
        "good": "1",
        "bad": "0",
        "replies": []
    },
    {
        "user_name": "HiddenPatriot2049",
        "time": "17 June, 2021",
        "context": "And along with the Chinese astronauts everything malicious to mankind",
        "good": "2",
        "bad": "0",
        "replies": []
    },
    {
        "user_name": "urdelusional",
        "time": "17 June, 2021",
        "context": "And without thanking us for the technology they stole.",
        "good": "1",
        "bad": "1",
        "replies": []
    },
    {
        "user_name": "jmhogoff",
        "time": "17 June, 2021",
        "context": "China trying to act like a world leader in Space Exploration all on stolen technology. Sorry but you got where you are on someone else's work/ brain power, not your own!  Snakes",
        "good": "3",
        "bad": "1",
        "replies": []
    },
    {
        "user_name": "QuanticoKid",
        "time": "17 June, 2021",
        "context": "They look like cardboard cutouts!",
        "good": "0",
        "bad": "0",
        "replies": []
    },
    {
        "user_name": "kilowattt245",
        "time": "17 June, 2021",
        "context": "When is somebody going to build the first space-station that has artificial gravity by spinning the space station as it orbits Earth?",
        "good": "2",
        "bad": "0",
        "replies": [
            {
                "user_name": "wmvan498",
                "time": "19 June, 2021",
                "context": "Elon will when he can find the time!",
                "good": "0",
                "bad": "0",
                "replies": []
            }
        ]
    },
    {
        "user_name": "iwillnotcomply..",
        "time": "17 June, 2021",
        "context": "Brought to you from Disney.",
        "good": "1",
        "bad": "0",
        "replies": []
    },
    {
        "user_name": "end_of_daze",
        "time": "17 June, 2021",
        "context": "Who out there suspects these Communists are plotting the course's for an attack from that Station on USA major cities and vital infrastructure. ? It's A Comin'.... Sooner that you think.",
        "good": "5",
        "bad": "0",
        "replies": [
            {
                "user_name": "noddingham",
                "time": "17 June, 2021",
                "context": "And the Dims are making fun of \"Space Force.\"",
                "good": "2",
                "bad": "0",
                "replies": []
            }
        ]
    },
    {
        "user_name": "dinglebert",
        "time": "18 June, 2021",
        "context": "Xi was so excited to see the astronauts off.  He was in front of all the spectators yelling \"Have a nice fright!!\"",
        "good": "1",
        "bad": "1",
        "replies": []
    },
    {
        "user_name": "SagittariusA*",
        "time": "17 June, 2021",
        "context": "They'll probably catch Chinese space covid while onboard the station. There's nothing really sanitary built in china.",
        "good": "4",
        "bad": "1",
        "replies": []
    },
    {
        "user_name": "Hondoxp589",
        "time": "18 June, 2021",
        "context": "...and I'll bet they spent half as much. Our space program is shackled down by congressional deals, spreading development and assembly all over the states so everyone gets a cut of the pie. They are more interested in spending the money then building anything. SpaceX is centralized, thinks out of the box and is motivated by profit. The Chi-Comms are centralized too. Design, build, and launch from one site. \nIf NASA can't do that, they need to get out of the rocket business. I can vision a future NASA that operates as a regulatory agency like the FAA, and if they need a rocket, buy one.",
        "good": "2",
        "bad": "0",
        "replies": []
    },
    {
        "user_name": "randyh558",
        "time": "17 June, 2021",
        "context": "Imagine China sending millions of Chinese into the space in the future, ET will say my god",
        "good": "1",
        "bad": "0",
        "replies": []
    },
    {
        "user_name": "don779",
        "time": "18 June, 2021",
        "context": "US: Bans China from ISS space station.\nChina: Fine, we’ll build our own space station.😂",
        "good": "8",
        "bad": "0",
        "replies": [
            {
                "user_name": "maryah",
                "time": "18 June, 2021",
                "context": "Let China spend a lot of money to build and maintain the space station. I think we should strengthen the blockade of China's science and technology and strengthen the secrecy of science and technology. Science and technology are the foundation of national development. Is it possible for the United States to get Chinese science and technology? China says, get out, America.",
                "good": "1",
                "bad": "0",
                "replies": [
                    {
                        "user_name": "djohnson",
                        "time": "18 June, 2021",
                        "context": "do you think they spend a lot of money ? , would you ride on a rocket that is built by 10 cents a day labor .",
                        "good": "0",
                        "bad": "0",
                        "replies": []
                    }
                ]
            }
        ]
    },
    {
        "user_name": "marienne2",
        "time": "24 June, 2021",
        "context": "Congratulations China!!!",
        "good": "1",
        "bad": "0",
        "replies": []
    },
    {
        "user_name": "Gael68",
        "time": "17 June, 2021",
        "context": "Any possibility they could launch a couple billion more Chinese up there?",
        "good": "0",
        "bad": "0",
        "replies": []
    },
    {
        "user_name": "jussiedoit",
        "time": "17 June, 2021",
        "context": "Why does it look like they're standing in gravity?",
        "good": "4",
        "bad": "0",
        "replies": []
    },
    {
        "user_name": "nomermac",
        "time": "17 June, 2021",
        "context": "I see a new part for Lebron James to play.\nHe could play Jaws in Muckraker.\nI'm tired of seeing him in the Progressive Commercials.\nAfter all, he would not want to get stereotyped.",
        "good": "0",
        "bad": "0",
        "replies": []
    },
    {
        "user_name": "WhoisJohnGalt850",
        "time": "17 June, 2021",
        "context": "Start analyzing the photos to figure out how much NASA technology they stole.",
        "good": "3",
        "bad": "0",
        "replies": [
            {
                "user_name": "maryah",
                "time": "18 June, 2021",
                "context": "They did not steal American technology. In order to prevent the advancement of China's aerospace technology, my country prohibited China from stealing US aerospace technology as early as 10 years ago. However, China learned from Russia. All three astronauts have studied English and Russian.",
                "good": "1",
                "bad": "0",
                "replies": []
            }
        ]
    },
    {
        "user_name": "rednek16",
        "time": "25 June, 2021",
        "context": "The travel time is down from the two days it took to reach China’s earlier experimental space stations, a result of a \"great many breakthroughs and innovations,\" the mission’s deputy chief designer, Gao Xu, told state broadcaster CCTV.\n\nNot the least of which was breaking through Western networks and firewalls to steal the technical information necessary for our achievements.",
        "good": "0",
        "bad": "0",
        "replies": []
    },
    {
        "user_name": "maryah",
        "time": "18 June, 2021",
        "context": "It is understood that China has learned from Russia the technology used to build the space station. They learned some technologies of the “”Russian Mir space station“”. We must look at the great harm that China and Russia’s military science and technology cooperation has caused to the United States.\n  Chinese astronauts once went to Russia's \"Gagarin Astronaut Training Center\" for space training.",
        "good": "2",
        "bad": "0",
        "replies": []
    },
    {
        "user_name": "dinglebert",
        "time": "18 June, 2021",
        "context": "Have a nice fright!",
        "good": "2",
        "bad": "0",
        "replies": []
    },
    {
        "user_name": "mrmosin762",
        "time": "17 June, 2021",
        "context": "Now they have a safe place to manufacture viruses and no one can prove it was them this time.",
        "good": "1",
        "bad": "3",
        "replies": []
    },
    {
        "user_name": "thunker54",
        "time": "18 June, 2021",
        "context": "Why cant two Chinese people have a white baby ?\nBecause two wongs don't make a white",
        "good": "2",
        "bad": "1",
        "replies": [
            {
                "user_name": "natasha205",
                "time": "21 June, 2021",
                "context": "Well, two Whites don't make a Wong either.",
                "good": "1",
                "bad": "0",
                "replies": []
            }
        ]
    },
    {
        "user_name": "paystub",
        "time": "17 June, 2021",
        "context": "Sure this is not in a studio. After all, Hollywood has been kissing up to China for some time.",
        "good": "0",
        "bad": "0",
        "replies": []
    },
    {
        "user_name": "WhatMeWorry651",
        "time": "17 June, 2021",
        "context": "\"great many breakthroughs and innovations,\" the mission’s deputy chief designer, Gao Xu, told state broadcaster CCTV.\n\"So the astronauts can have a good rest in space which should make them less tired,\" Gao said.\n\nSo, are you going to say 'Thank you United States of America, and sorry we stole your proprietary information from JPL and NASA'?",
        "good": "1",
        "bad": "0",
        "replies": []
    },
    {
        "user_name": "dinglebert",
        "time": "18 June, 2021",
        "context": "BLM said the Chinese are racist because there isn't a black guy in the photo.",
        "good": "5",
        "bad": "0",
        "replies": []
    },
    {
        "user_name": "rightshoe",
        "time": "18 June, 2021",
        "context": "I wonder which one is the political officer.",
        "good": "2",
        "bad": "0",
        "replies": []
    },
    {
        "user_name": "dinglebert",
        "time": "19 June, 2021",
        "context": "When those guys were in college they all took up space.",
        "good": "0",
        "bad": "0",
        "replies": []
    },
    {
        "user_name": "djohnson",
        "time": "18 June, 2021",
        "context": "They have the cameras ready , and are plotting the locations of all the American military satellites , Have they're 4 million frozen embryos  \nNow the CCP can launch the big \"bio Weapon\"  against the world .",
        "good": "0",
        "bad": "1",
        "replies": []
    },
    {
        "user_name": "tjmoon",
        "time": "17 June, 2021",
        "context": "Spacecraft built by Chinese contractors.  No thanks.",
        "good": "2",
        "bad": "0",
        "replies": [
            {
                "user_name": "maryah",
                "time": "18 June, 2021",
                "context": "If Russia provides science and technology to help China increase its strength, then we must be vigilant. All countries should prohibit the spread of science and technology to China or the sale of products with scientific and technological content to China.",
                "good": "1",
                "bad": "0",
                "replies": []
            }
        ]
    },
    {
        "user_name": "dan5047628",
        "time": "18 June, 2021",
        "context": "They have gravity on their space station??",
        "good": "1",
        "bad": "0",
        "replies": []
    },
    {
        "user_name": "NoNo329",
        "time": "17 June, 2021",
        "context": "Well, DoD had better take a break from their 'WOKE' training and be on the look out for satellite destroying space mines to suddenly appear... along with other such sundry dirty space tricks, now that Uncle Joe's Chi-com friends are buzzing around the hood...",
        "good": "1",
        "bad": "0",
        "replies": []
    },
    {
        "user_name": "d7602002",
        "time": "17 June, 2021",
        "context": "Part of the story they left out, by the time Americans figured out how to pronounce their names, they were back on Earth.",
        "good": "1",
        "bad": "0",
        "replies": []
    },
    {
        "user_name": "broadwayltd235",
        "time": "4 July, 2021",
        "context": "cmon gimme a break.  we're already at war with china.  nancy,chuck, joe and bernie are the chinese front line",
        "good": "0",
        "bad": "0",
        "replies": []
    }
]