{
    "URL": "https://www.foxnews.com/us/fbi-makes-6000-arrests-seizes-firearms-fentanyl-massive-summer-long-operation",
    "title": "FBI makes 6,000 arrests, seizes firearms and fentanyl in massive summer-long operation",
    "subtitle": "The FBI announced thousands of arrests and firearms and drug seizures as violent crime has spiked in cities across the country",
    "published_date": "September 15, 2022 7:11pm EDT",
    "extracted_date": "2022/09/25 12:36:27",
    "author_name": "Paul Best",
    "author": "https://www.foxnews.com/person/b/paul-best",
    "are_no_replies": false,
    "comment_count": 233,
    "real_comment_count": "235"
}