{
    "URL": "https://www.foxnews.com/science/spacex-returns-4-astronauts-to-earth-ending-200-day-flight",
    "title": "SpaceX returns 4 astronauts to Earth, ending 200-day flight",
    "subtitle": "The capsule parachuted into the Gulf of Mexico off the coast of Pensacola, Florida, in darkness",
    "published_date": "November 8, 2021 11:12pm EST",
    "extracted_date": "2022/09/27 16:55:44",
    "author_name": "Associated Press",
    "author": "http://www.ap.org/",
    "are_no_replies": false,
    "comment_count": 353,
    "real_comment_count": "409"
}